{
    "stock": [
        {
            "name": "moho",
            "label": "Moho",
            "radius": 250000,
            "grav_sea_level": 2.7,
            "satellites": []
        },
        {
            "name": "eve",
            "label": "Eve",
            "radius": 700000,
            "grav_sea_level": 16.7,
            "satellites": [
                {
                    "name": "gilly",
                    "label": "Gilly",
                    "radius": 13000,
                    "grav_sea_level": 0.049
                }
            ]
        },
        {
            "name": "kerbin",
            "label": "Kerbin",
            "radius": 600000,
            "grav_sea_level": 9.8,
            "satellites": [
                {
                    "name": "mun",
                    "label": "Mun",
                    "radius": 200000,
                    "grav_sea_level": 1.63
                },
                {
                    "name": "minmus",
                    "label": "MinMus",
                    "radius": 60000,
                    "grav_sea_level": 0.491
                }
            ]
        },
        {
            "name": "duna",
            "label": "Duna",
            "radius": 320000,
            "grav_sea_level": 2.94,
            "satellites": [
                {
                    "name": "ike",
                    "label": "Ike",
                    "radius": 130000,
                    "grav_sea_level": 1.1
                }
            ]
        },
        {
            "name": "dres",
            "label": "Dres",
            "radius": 138000,
            "grav_sea_level": 1.13,
            "satellites": []
        },
        {
            "name": "jool",
            "label": "Jool",
            "radius": 6000000,
            "grav_sea_level": 7.85,
            "satellites": [
                {
                    "name": "laythe",
                    "label": "Laythe",
                    "radius": 500000,
                    "grav_sea_level": 7.85
                },
                {
                    "name": "vall",
                    "label": "Vall",
                    "radius": 300000,
                    "grav_sea_level": 2.31
                },
                {
                    "name": "tylo",
                    "label": "Tylo",
                    "radius": 600000,
                    "grav_sea_level": 7.85
                },
                {
                    "name": "bop",
                    "label": "Bop",
                    "radius": 65000,
                    "grav_sea_level": 0.589
                },
                {
                    "name": "pol",
                    "label": "Pol",
                    "radius": 44000,
                    "grav_sea_level": 0.373
                }
            ]
        },
        {
            "name": "eeloo",
            "label": "Eeloo",
            "radius": 210000,
            "grav_sea_level": 1.69,
            "satellites": []
        }
    ]
}